arraylake/__init__.py
arraylake/__main__.py
arraylake/_version.py
arraylake/api_utils.py
arraylake/asyn.py
arraylake/client.py
arraylake/config.py
arraylake/config.yaml
arraylake/credentials.py
arraylake/diagnostics.py
arraylake/exceptions.py
arraylake/log_util.py
arraylake/py.typed
arraylake/token.py
arraylake/tuning.py
arraylake/types.py
arraylake/cli/__init__.py
arraylake/cli/auth.py
arraylake/cli/compute.py
arraylake/cli/config.py
arraylake/cli/main.py
arraylake/cli/repo.py
arraylake/cli/utils.py
arraylake/compute/doctor.py
arraylake/compute/http_client.py
arraylake/compute/services.py
arraylake/compute/types.py
arraylake/display/__init__.py
arraylake/display/repo.py
arraylake/display/repolist.py
arraylake/metastore/__init__.py
arraylake/metastore/abc.py
arraylake/metastore/http_metastore.py
arraylake/repos/__init__.py
arraylake/repos/icechunk/__init__.py
arraylake/repos/icechunk/storage.py
arraylake/repos/icechunk/types.py
arraylake/repos/icechunk/virtual.py
arraylake-0.29.0.dist-info/METADATA
arraylake-0.29.0.dist-info/WHEEL
arraylake-0.29.0.dist-info/entry_points.txt
arraylake-0.29.0.dist-info/RECORD
